plaster/__init__.py
plaster/exceptions.py
plaster/interfaces.py
plaster/loaders.py
plaster/protocols.py
plaster/uri.py
plaster-1.1.2.dist-info/LICENSE.txt
plaster-1.1.2.dist-info/METADATA
plaster-1.1.2.dist-info/WHEEL
plaster-1.1.2.dist-info/top_level.txt
plaster-1.1.2.dist-info/RECORD
