Metadata-Version: 2.1
Name: plaster
Version: 1.1.2
Summary: A loader interface around multiple config file formats.
Home-page: https://docs.pylonsproject.org/projects/plaster/en/latest/
Author: Michael Merickel
Author-email: pylons-discuss@googlegroups.com
Keywords: plaster,pastedeploy,ini,config
Classifier: Development Status :: 5 - Production/Stable
Classifier: Intended Audience :: Developers
Classifier: License :: OSI Approved :: MIT License
Classifier: Natural Language :: English
Classifier: Programming Language :: Python :: 3
Classifier: Programming Language :: Python :: 3.7
Classifier: Programming Language :: Python :: 3.8
Classifier: Programming Language :: Python :: 3.9
Classifier: Programming Language :: Python :: 3.10
Classifier: Programming Language :: Python :: 3.11
Classifier: Programming Language :: Python :: Implementation :: CPython
Classifier: Programming Language :: Python :: Implementation :: PyPy
Requires-Python: >=3.7
Provides-Extra: docs
Provides-Extra: testing
License-File: LICENSE.txt
